bulkergr_api/__init__.py
bulkergr_api/bulkergr_api.py
bulkergr_api/cli.py
bulkergr_api/exceptions.py
bulkergr_api-0.1.4.dist-info/AUTHORS.rst
bulkergr_api-0.1.4.dist-info/LICENSE
bulkergr_api-0.1.4.dist-info/METADATA
bulkergr_api-0.1.4.dist-info/WHEEL
bulkergr_api-0.1.4.dist-info/entry_points.txt
bulkergr_api-0.1.4.dist-info/top_level.txt
bulkergr_api-0.1.4.dist-info/RECORD
