Metadata-Version: 2.1
Name: bulkergr-api
Version: 0.1.4
Summary: A Python Client for v1.0 of Bulker.gr SMS HTTP API
Home-page: https://github.com/negletios/bulkergr_api
Author: Yiannis Inglessis 
Author-email: negtheone@gmail.com
License: MIT license
Keywords: bulkergr_api
Platform: UNKNOWN
Classifier: Development Status :: 2 - Pre-Alpha
Classifier: Intended Audience :: Developers
Classifier: License :: OSI Approved :: MIT License
Classifier: Natural Language :: English
Classifier: Programming Language :: Python :: 2
Classifier: Programming Language :: Python :: 2.7
Classifier: Programming Language :: Python :: 3
Classifier: Programming Language :: Python :: 3.4
Classifier: Programming Language :: Python :: 3.5
Classifier: Programming Language :: Python :: 3.6
Classifier: Programming Language :: Python :: 3.7
Requires-Dist: requests (>=2.5.0)
